daze_python-0.1.0.dist-info/licenses/LICENSE
strpro/__init__.py
strpro/utils.py
daze_python-0.1.0.dist-info/METADATA
daze_python-0.1.0.dist-info/WHEEL
daze_python-0.1.0.dist-info/top_level.txt
daze_python-0.1.0.dist-info/RECORD
